awswhitelist/__init__.py
awswhitelist/__version__.py
awswhitelist/config.py
awswhitelist/main.py
awswhitelist/py.typed
awswhitelist/aws/__init__.py
awswhitelist/aws/service.py
awswhitelist/mcp/__init__.py
awswhitelist/mcp/handler.py
awswhitelist/utils/__init__.py
awswhitelist/utils/credential_validator.py
awswhitelist/utils/ip_validator.py
awswhitelist/utils/logging.py
awswhitelist_mcp-1.1.10.dist-info/licenses/LICENSE
awswhitelist_mcp-1.1.10.dist-info/METADATA
awswhitelist_mcp-1.1.10.dist-info/WHEEL
awswhitelist_mcp-1.1.10.dist-info/entry_points.txt
awswhitelist_mcp-1.1.10.dist-info/top_level.txt
awswhitelist_mcp-1.1.10.dist-info/RECORD
