Metadata-Version: 2.4
Name: awswhitelist_mcp
Version: 1.1.10
Summary: MCP server for AWS Security Group IP whitelisting with stateless credential handling
Home-page: https://github.com/dbbuilder/awswhitelist2
Author: DBBuilder
Author-email: dbbuilderio@gmail.com
License: MIT
Keywords: aws,security-group,mcp,model-context-protocol,whitelist,ip-management
Classifier: Development Status :: 4 - Beta
Classifier: Intended Audience :: Developers
Classifier: Intended Audience :: System Administrators
Classifier: Topic :: Software Development :: Libraries :: Python Modules
Classifier: Topic :: System :: Systems Administration
Classifier: Topic :: Security
Classifier: Programming Language :: Python :: 3
Classifier: Programming Language :: Python :: 3.8
Classifier: Programming Language :: Python :: 3.9
Classifier: Programming Language :: Python :: 3.10
Classifier: Programming Language :: Python :: 3.11
Classifier: Programming Language :: Python :: 3.12
Classifier: Operating System :: OS Independent
Classifier: Environment :: Console
Requires-Python: >=3.8
License-File: LICENSE
Requires-Dist: boto3>=1.34.0
Requires-Dist: botocore>=1.34.0
Requires-Dist: python-json-logger>=2.0.7
Requires-Dist: pydantic>=2.5.0
Requires-Dist: requests>=2.28.0
Dynamic: author
Dynamic: author-email
Dynamic: classifier
Dynamic: description
Dynamic: description-content-type
Dynamic: home-page
Dynamic: keywords
Dynamic: license
Dynamic: license-file
Dynamic: requires-dist
Dynamic: requires-python
Dynamic: summary
